colang/__init__.py
colang-0.0.1.dist-info/LICENSE
colang-0.0.1.dist-info/WHEEL
colang-0.0.1.dist-info/METADATA
colang-0.0.1.dist-info/RECORD
