Metadata-Version: 2.1
Name: colang
Version: 0.0.1
Summary: Clean, intuitive, and powerful modeling language for Conversational AI.
Author: Razvan Dinu
Author-email: razvan@colang.ai
Classifier: Programming Language :: Python :: 2
Classifier: Programming Language :: Python :: 2.7
Classifier: Programming Language :: Python :: 3
Classifier: Programming Language :: Python :: 3.4
Classifier: Programming Language :: Python :: 3.5
Classifier: Programming Language :: Python :: 3.6
Classifier: Programming Language :: Python :: 3.7
Classifier: Programming Language :: Python :: 3.8
Requires-Dist: requests (>=2.24.0,<3.0.0)
